pyhandy/__init__.py
pyhandy/context.py
pyhandy/hashtool.py
pyhandy/perf.py
pyhandy/rand.py
pyhandy/sort.py
pyhandy-0.0.10.dist-info/LICENSE
pyhandy-0.0.10.dist-info/METADATA
pyhandy-0.0.10.dist-info/WHEEL
pyhandy-0.0.10.dist-info/top_level.txt
pyhandy-0.0.10.dist-info/RECORD
